qcg/pilotjob/cmds/__init__.py
qcg/pilotjob/cmds/_version.py
qcg/pilotjob/cmds/processes.py
qcg/pilotjob/cmds/report.py
qcg_pilotjob_cmds-0.14.2.dist-info/METADATA
qcg_pilotjob_cmds-0.14.2.dist-info/WHEEL
qcg_pilotjob_cmds-0.14.2.dist-info/entry_points.txt
qcg_pilotjob_cmds-0.14.2.dist-info/top_level.txt
qcg_pilotjob_cmds-0.14.2.dist-info/RECORD
