Metadata-Version: 2.4
Name: qcg-pilotjob-cmds
Version: 0.14.2
Summary: Manage many jobs inside one allocation
Home-page: http://github.com/vecma-project/QCG-PilotJob
Author: Piotr Kopta
Author-email: pkopta@man.poznan.pl
Requires-Dist: qcg-pilotjob
Requires-Dist: termcolor
Requires-Dist: prompt_toolkit
Requires-Dist: plotly_express>=0.4.1
Requires-Dist: pandas
Requires-Dist: kaleido
Dynamic: author
Dynamic: author-email
Dynamic: description
Dynamic: description-content-type
Dynamic: home-page
Dynamic: requires-dist
Dynamic: summary
